utils/__init__.py
utils/__string.py
utils/_assets/_file/linux/7zz
utils/_assets/_file/linux/7zzs
utils/_assets/_file/linux/rar
utils/_assets/_file/linux/unrar
utils/_assets/_file/mac/7zz
utils/_assets/_file/mac/rar
utils/_assets/_file/mac/unrar
utils/_assets/_file/win/7zr.exe
utils/_assets/_file/win/Rar.exe
utils/_assets/_file/win/UnRAR.exe
utils/_assets.py
utils/_cookies.py
utils/_datetime.py
utils/_execute.py
utils/_file.py
utils/_headers.py
utils/_html.py
utils/_image.py
utils/_list.py
utils/_logger.py
utils/_math.py
utils/_pandas.py
utils/_sql.py
utils/_types.py
utils/_url.py
utils/_validators.py
cwb_utils-0.1.5.dist-info/METADATA
cwb_utils-0.1.5.dist-info/WHEEL
cwb_utils-0.1.5.dist-info/licenses/LICENSE
cwb_utils-0.1.5.dist-info/RECORD
